delaunayextrapolation.py
delaunayextrapolation-0.3.dist-info/METADATA
delaunayextrapolation-0.3.dist-info/WHEEL
delaunayextrapolation-0.3.dist-info/RECORD
