Metadata-Version: 2.1
Name: delaunayextrapolation
Version: 0.3
Summary: Delaunay Extrapolation.
License: MIT
Author: vitroid
Author-email: vitroid@gmail.com
Requires-Python: >=3.10,<4.0
Classifier: License :: OSI Approved :: MIT License
Classifier: Programming Language :: Python :: 3
Classifier: Programming Language :: Python :: 3.10
Classifier: Programming Language :: Python :: 3.11
Classifier: Programming Language :: Python :: 3.12
Requires-Dist: numpy (>=2.1.1,<3.0.0)
Requires-Dist: scipy (>=1.14.0,<2.0.0)
